openalex_matching/__init__.py
openalex_matching/csv_handler.py
openalex_matching/person_match.py
openalex_matching/search_py.py
openalex_matching/topic_orcid_algorithms.py
openalex_matching-0.5.dist-info/METADATA
openalex_matching-0.5.dist-info/WHEEL
openalex_matching-0.5.dist-info/top_level.txt
openalex_matching-0.5.dist-info/RECORD
